{
  "headline": "Long Before President’s Drone Strike, Iran Hawks Pushed for the Killing of a General",
  "abstract": "Neoconservatives have long urged action against Iran, just as they once did about Iraq. Now, Maj. Gen. Qassim Suleimani is dead.",
  "lead_paragraph": "WASHINGTON — Years before President Trump ordered the killing of Maj. Gen. Qassim Suleimani, Reuel Marc Gerecht, a former C.I.A. officer and prominent neoconservative commentator, had recommended taking out the notorious Iranian general.",
  "keywords": [
    "United States International Relations",
    "United States Politics and Government",
    "Targeted Killings",
    "United States Defense and Military Forces",
    "Bolton, John R",
    "Trump, Donald J",
    "Suleimani, Qassim",
    "Carlson, Tucker",
    "Cheney, Dick",
    "Cheney, Liz",
    "Gerecht, Reuel Marc",
    "Iraq",
    "Iran",
    "Middle East"
  ],
  "print_page": "10"
}