{
  "headline": "Paperback Row",
  "abstract": "Six new paperbacks to check out this week.",
  "lead_paragraph": "THE SCHOOLHOUSE GATE: Public Education, the Supreme Court, and the Battle for the American Mind, by Justin Driver. (Vintage, $17.95.) Driver, a Yale law professor, surveys the history of legal controversies over students’ rights in public schools, including segregation, flag saluting and corporal punishment, which is still legal in 22 states. Our reviewer, Dana Goldstein, called the book “indispensable.” ",
  "keywords": [
    "Books and Literature",
    "The Schoolhouse Gate: Public Education, the Supreme Court, and the Battle for the American Mind (Book)",
    "Driver, Justin (Scholar)",
    "The Patch (Book)",
    "McPhee, John",
    "Barracoon (Book)",
    "Hurston, Zora Neale",
    "The Lost Man (Book)",
    "Harper, Jane",
    "The Man With the Sawed-Off Leg: And Other Tales of a New York City Block (Book)",
    "Wakin, Daniel J",
    "Ghost Wall: A Novel (Book)",
    "Moss, Sarah (1975- )"
  ],
  "print_page": "20"
}