{
  "headline": null,
  "abstract": "Mr. Biden’s total, while far short of the haul that Senator Bernie Sanders announced earlier Thursday, was an improvement from the previous quarter.",
  "lead_paragraph": "WASHINGTON — Joseph R. Biden Jr. said on Thursday that he had raised $22.7 million in the fourth quarter of 2019, a significant improvement from his lackluster fund-raising performance in the previous three months.",
  "keywords": [
    "Campaign Finance",
    "Biden, Joseph R Jr",
    "Presidential Election of 2020",
    "United States Politics and Government"
  ],
  "print_page": null
}