{
  "headline": "Macron Pulls Back in Pension Brawl With Strikers",
  "abstract": "Faced with an unrelenting protest over proposed changes in France’s generous pension system, officials withdraw a move to raise the full-benefit retirement age to 64 from the present 62.",
  "lead_paragraph": "PARIS — With tens of thousands of anti-government demonstrators once again coursing through the streets of Paris and other cities and clouds of tear gas and smashed store windows punctuating the urban landscape, the French government made a major concession on Saturday to unions protesting its pension reform plan.",
  "keywords": [
    "Retirement",
    "Organized Labor",
    "French Democratic Confederation of Labor",
    "Macron, Emmanuel (1977- )",
    "Pensions and Retirement Plans",
    "France"
  ],
  "print_page": "4"
}