{
  "headline": "Communal Living by Way of Capitalism Is Growing",
  "abstract": "As co-living companies race to open projects in New York, the options for renters are multiplying.",
  "lead_paragraph": "New Yorkers have long shared apartments in order to afford the city’s famously high rents. This, of course, often entails hunting down an apartment with a real estate agent — and paying a broker’s fee, plus a hefty deposit — then furnishing the place, lining up roommates and getting electricity and internet service up and running.",
  "keywords": [
    "Real Estate and Housing (Residential)",
    "Renting and Leasing (Real Estate)",
    "Roommates"
  ],
  "print_page": "6"
}