{
  "headline": "Stabbing Victim in Anti-Semitic Rampage Is Unlikely to Awaken From Coma, Family Says",
  "abstract": "“Doctors are not optimistic,” the man’s relatives said several days after the stabbing attack at a Hanukkah celebration left him with likely brain damage.",
  "lead_paragraph": "The most grievously injured victim of an anti-Semitic mass stabbing attack in a New York City suburb remains in a coma and is unlikely to awaken, his relatives said on Tuesday night.",
  "keywords": [
    "Jews and Judaism",
    "ANTI-SEMITISM",
    "Murders, Attempted Murders and Homicides",
    "Hasidism",
    "Discrimination",
    "Hate Crimes",
    "Thomas, Grafton E (1982- )",
    "MONSEY (NY)",
    "Rockland County (NY)",
    "Neumann, Josef",
    "Gluck, Jacob",
    "Frank, Naftuli"
  ],
  "print_page": "15"
}