{
  "headline": "Georgian Rarities, Served Without Fanfare",
  "abstract": "This Chelsea restaurant, where gandzili, a cousin to ramps, is served alongside the better-known adjaruli khachapuri, honors the cuisine’s rustic simplicity.",
  "lead_paragraph": "Ekala is a prickly climber akin to North American greenbrier, often dismissed as a troublemaking weed. In the Imereti region of Georgia, its crisp young shoots are gathered in spring, before their thorns sharpen, when they’re as skinny and fragile as first asparagus, and pickled to last.",
  "keywords": [
    "Restaurants",
    "Chelsea (Manhattan, NY)",
    "Georgia (Georgian Republic)",
    "Chama Mama (Manhattan, NY, Restaurant)"
  ],
  "print_page": "3"
}