{
  "headline": "Technology Throws a Curveball to a Sport Built on Deceit",
  "abstract": "Baseball’s sign-stealing scandal reflects a blurred line between being clever and breaking rules, a distinction that baseball and its unique codes of behavior have long wrestled with.",
  "lead_paragraph": "At the heart of baseball’s sign-stealing scandal is the sport’s long struggle with technology and its inconsistent drawing of a line between gamesmanship and cheating.",
  "keywords": [
    "Baseball",
    "Cheating",
    "Major League Baseball",
    "Houston Astros"
  ],
  "print_page": "9"
}