{
  "headline": null,
  "abstract": "People for the Ethical Treatment of Animals has called on California racing officials to suspend racing at the track.",
  "lead_paragraph": "It was a grim trifecta and a familiar result for Santa Anita Park: Three horses died in three days this past weekend at California’s best known and most scrutinized racetrack.",
  "keywords": [
    "Santa Anita Derby",
    "Animal Abuse, Rights and Welfare",
    "ACCIDENTS AND SAFETY",
    "Horse Racing",
    "California Horse Racing Board",
    "National Thoroughbred Racing Assn",
    "People for the Ethical Treatment of Animals",
    "Santa Anita Park (Calif)",
    "Stronach Group",
    "ARCADIA (CALIF)"
  ],
  "print_page": null
}