{
  "headline": "Psychologist Who Used Waterboarding Will Testify at Guantánamo",
  "abstract": "James Mitchell will be the first witness to describe the torture of detainees in the secret prisons — some at his own hands — in the trial of the men accused of plotting the Sept. 11 attacks.",
  "lead_paragraph": "This article was produced in partnership with the Pulitzer Center on Crisis Reporting.",
  "keywords": [
    "Interrogations",
    "Detainees",
    "Torture",
    "Terrorism",
    "September 11 (2001)",
    "Military Tribunals",
    "AL QAEDA",
    "Central Intelligence Agency",
    "Senate Committee on Intelligence",
    "Mitchell, James E",
    "Jessen, Bruce",
    "Mohammed, Khalid Shaikh",
    "Haspel, Gina",
    "Zubaydah, Abu",
    "Guantanamo Bay Naval Base (Cuba)",
    "United States Politics and Government"
  ],
  "print_page": "15"
}