{
  "headline": null,
  "abstract": "Schurman Fine Papers, which also owns American Greetings and Carlton Card stores, filed for bankruptcy on Thursday.",
  "lead_paragraph": "The latest victim of the retail apocalypse? Birthday cards.",
  "keywords": [
    "Greeting Cards",
    "Stationery",
    "Papyrus (Retailer)",
    "American Greetings Corp Inc",
    "Carlton Cards Ltd",
    "Schurman Retail Group",
    "Shutdowns (Institutional)",
    "Bankruptcies",
    "Shopping and Retail",
    "Shopping Centers and Malls"
  ],
  "print_page": null
}