{
  "headline": "An Iron Fist With Flaws A Virus Can Fit Through",
  "abstract": "While China can mobilize a huge national response to the outbreak, its response to the crisis is also a lesson in how the country’s political weak points can carry grave consequences for world health.",
  "lead_paragraph": "It was the initial news reports that first suggested China’s political system might be getting in the way of its ability to confront the coronavirus outbreak.",
  "keywords": [
    "Coronavirus (2019-nCoV)",
    "China",
    "Politics and Government",
    "SARS (Severe Acute Respiratory Syndrome)",
    "Epidemics",
    "Xi Jinping",
    "Regulation and Deregulation of Industry"
  ],
  "print_page": "12"
}