{
  "headline": "Caribbean Patties, Traditional and Not",
  "abstract": "Kafe Louverture, in Bedford-Stuyvesant, and Branch Patty, at Artists & Fleas Williamsburg, make two variations on the beloved treat.",
  "lead_paragraph": "If you took a slow-motion video of yourself biting into a Haitian patty at Kafe Louverture in Bedford-Stuyvesant, Brooklyn, it would look like this: The outer layer of pastry would shatter dramatically, like powdery snow blasting off a pair of skis. Then your teeth would sink into the gently simmered filling — beef or lamb, maybe, punctuated with sprightly flecks of pepper.",
  "keywords": [
    "Restaurants",
    "Haitian-Americans",
    "JAMAICAN-AMERICANS",
    "Brooklyn (NYC)",
    "Branch Patty (Brooklyn, NY, Restaurant)",
    "Kafe Louverture (Brooklyn, NY, Restaurant)"
  ],
  "print_page": "8"
}