{
  "headline": "For Basketball Fans, Collective Mourning Without Comparison",
  "abstract": "Older Americans remember where they were when they learned about J.F.K.’s death. Now basketball fans have their own terrible moment.",
  "lead_paragraph": "To be a basketball fan is to rank the star you’re watching with the stars you have seen before, constantly searching for the precise comparison.",
  "keywords": [
    "Basketball",
    "National Basketball Assn",
    "Los Angeles Lakers",
    "Bryant, Kobe"
  ],
  "print_page": "9"
}