{
  "headline": null,
  "abstract": "New DNA technology helped officials crack a case that had stalled for a dozen years.",
  "lead_paragraph": "In 2007, a fisherman discovered an infant’s remains in a sealed container in a waterway near Sacramento. Efforts to identify the child, who had died of blunt force trauma, were unsuccessful, and the investigation into the killing stalled for a dozen years.",
  "keywords": [
    "Murders, Attempted Murders and Homicides",
    "Forensic Science",
    "Child Abuse and Neglect",
    "DNA (Deoxyribonucleic Acid)",
    "Justice Department",
    "Sacramento (Calif)"
  ],
  "print_page": null
}