{
  "headline": "Overloaded Pharmacists Warn They’re Making Fatal Mistakes",
  "abstract": "Pharmacists across the U.S. warn that the push to do more with less has made medication errors more likely. “I am a danger to the public,” one wrote to a regulator.",
  "lead_paragraph": "For Alyssa Watrous, the medication mix-up meant a pounding headache, nausea and dizziness. In September, Ms. Watrous, a 17-year-old from Connecticut, was about to take another asthma pill when she realized CVS had mistakenly given her blood pressure medication intended for someone else.",
  "keywords": [
    "Drugs (Pharmaceuticals)",
    "ACCIDENTS AND SAFETY",
    "Drugstores",
    "CVS Caremark Corporation",
    "Regulation and Deregulation of Industry",
    "Health Insurance and Managed Care",
    "Walgreen Co.",
    "Medicine and Health"
  ],
  "print_page": "1"
}