{
  "headline": null,
  "abstract": "She became a world-renowned author writing about “nice people whose lives are invaded.”",
  "lead_paragraph": "Mary Higgins Clark, a fixture on best-seller lists for decades and a writer whose more than 50 novels earned her the sobriquet Queen of Suspense, died on Friday in Naples, Fla. She was 92.",
  "keywords": [
    "Clark, Carol Higgins",
    "Writing and Writers",
    "Books and Literature",
    "Deaths (Obituaries)",
    "Clark, Mary Higgins"
  ],
  "print_page": null
}