{
  "headline": "Speedy and Unerring, A.I. Comes to the Operating Room",
  "abstract": "Images made by lasers and read by computers can help speed up the diagnosis of brain tumors during surgery.",
  "lead_paragraph": "Brain surgeons are bringing artificial intelligence and new imaging techniques into the operating room, to diagnose tumors as accurately as pathologists, and much faster, according to a report in the journal Nature Medicine.",
  "keywords": [
    "Brain Cancer",
    "Surgery and Surgeons",
    "ARTIFICIAL INTELLIGENCE",
    "Tissue (Human)",
    "Tumors",
    "Nature Medicine (Journal)",
    "Laser (Light Amplification by Stimulated Emission of Radiation)",
    "Orringer, Daniel A",
    "your-feed-healthcare"
  ],
  "print_page": "6"
}