{
  "headline": "A Threat to Iran’s Rich Cultural Heritage",
  "abstract": "Leaders of several organizations say President Trump’s threat to destroy Iranian sites would be a war crime and contrary to American policy. Also: Marrying a former partner for the second time.",
  "lead_paragraph": "To the Editor:",
  "keywords": [
    "Destruction of Cultural Antiquities and Heritage",
    "Trump, Donald J",
    "ARCHAEOLOGICAL INSTITUTE OF AMERICA",
    "Iran",
    "Marriages"
  ],
  "print_page": "22"
}